{
    "sourceFile": "src/components/Sidebar.jsx",
    "activeCommit": 0,
    "commits": [
        {
            "activePatchIndex": 9,
            "patches": [
                {
                    "date": 1766862734823,
                    "content": "Index: \n===================================================================\n--- \n+++ \n"
                },
                {
                    "date": 1766863786834,
                    "content": "Index: \n===================================================================\n--- \n+++ \n@@ -7,9 +7,9 @@\n         <h4 className=\"fw-bold\">Unlock</h4>\n       </div>\n \n       <ul className=\"list-group list-group-flush mt-3\">\n-        <Link to=\"/dashboard\" className=\"list-group-item list-group-item-action\">\n+        <Link to=\"/dashboard/publisher\" className=\"list-group-item list-group-item-action\">\n           <i className=\"bi bi-speedometer2 me-2\"></i> Dashboard\n         </Link>\n \n         <Link to=\"/events\" className=\"list-group-item list-group-item-action\">\n"
                },
                {
                    "date": 1766863795683,
                    "content": "Index: \n===================================================================\n--- \n+++ \n@@ -11,9 +11,9 @@\n         <Link to=\"/dashboard/publisher\" className=\"list-group-item list-group-item-action\">\n           <i className=\"bi bi-speedometer2 me-2\"></i> Dashboard\n         </Link>\n \n-        <Link to=\"/events\" className=\"list-group-item list-group-item-action\">\n+        <Link to=\"/dashboard/publisher/events\" className=\"list-group-item list-group-item-action\">\n           <i className=\"bi bi-calendar-event me-2\"></i> Events\n         </Link>\n \n         <Link to=\"/jobs\" className=\"list-group-item list-group-item-action\">\n"
                },
                {
                    "date": 1766863850661,
                    "content": "Index: \n===================================================================\n--- \n+++ \n@@ -15,9 +15,9 @@\n         <Link to=\"/dashboard/publisher/events\" className=\"list-group-item list-group-item-action\">\n           <i className=\"bi bi-calendar-event me-2\"></i> Events\n         </Link>\n \n-        <Link to=\"/jobs\" className=\"list-group-item list-group-item-action\">\n+        <Link to=\"/\" className=\"list-group-item list-group-item-action\">\n           <i className=\"bi bi-briefcase me-2\"></i> Jobs\n         </Link>\n \n         <Link to=\"/funding-calls\" className=\"list-group-item list-group-item-action\">\n"
                },
                {
                    "date": 1766863939820,
                    "content": "Index: \n===================================================================\n--- \n+++ \n@@ -15,13 +15,13 @@\n         <Link to=\"/dashboard/publisher/events\" className=\"list-group-item list-group-item-action\">\n           <i className=\"bi bi-calendar-event me-2\"></i> Events\n         </Link>\n \n-        <Link to=\"/\" className=\"list-group-item list-group-item-action\">\n+        <Link to=\"/dashboard/publisher/jobs\" className=\"list-group-item list-group-item-action\">\n           <i className=\"bi bi-briefcase me-2\"></i> Jobs\n         </Link>\n \n-        <Link to=\"/funding-calls\" className=\"list-group-item list-group-item-action\">\n+        <Link to=\"/dashboard/publisher/funding-calls\" className=\"list-group-item list-group-item-action\">\n           <i className=\"bi bi-cash-stack me-2\"></i> Startup Funding Calls\n         </Link>\n \n         <Link to=\"/investor-programs\" className=\"list-group-item list-group-item-action\">\n"
                },
                {
                    "date": 1766863949470,
                    "content": "Index: \n===================================================================\n--- \n+++ \n@@ -23,9 +23,9 @@\n         <Link to=\"/dashboard/publisher/funding-calls\" className=\"list-group-item list-group-item-action\">\n           <i className=\"bi bi-cash-stack me-2\"></i> Startup Funding Calls\n         </Link>\n \n-        <Link to=\"/investor-programs\" className=\"list-group-item list-group-item-action\">\n+        <Link to=\"\" className=\"list-group-item list-group-item-action\">\n           <i className=\"bi bi-graph-up-arrow me-2\"></i> Investor Programs\n         </Link>\n \n         <Link to=\"/competitions\" className=\"list-group-item list-group-item-action\">\n"
                },
                {
                    "date": 1766863980763,
                    "content": "Index: \n===================================================================\n--- \n+++ \n@@ -23,13 +23,13 @@\n         <Link to=\"/dashboard/publisher/funding-calls\" className=\"list-group-item list-group-item-action\">\n           <i className=\"bi bi-cash-stack me-2\"></i> Startup Funding Calls\n         </Link>\n \n-        <Link to=\"\" className=\"list-group-item list-group-item-action\">\n+        <Link to=\"/dashboard/publisher/investor-programs\" className=\"list-group-item list-group-item-action\">\n           <i className=\"bi bi-graph-up-arrow me-2\"></i> Investor Programs\n         </Link>\n \n-        <Link to=\"/competitions\" className=\"list-group-item list-group-item-action\">\n+        <Link to=\"/dashboard/publisher/competitions\" className=\"list-group-item list-group-item-action\">\n           <i className=\"bi bi-trophy me-2\"></i> Competitions\n         </Link>\n \n         <Link to=\"/workshops\" className=\"list-group-item list-group-item-action\">\n"
                },
                {
                    "date": 1766863990118,
                    "content": "Index: \n===================================================================\n--- \n+++ \n@@ -31,9 +31,9 @@\n         <Link to=\"/dashboard/publisher/competitions\" className=\"list-group-item list-group-item-action\">\n           <i className=\"bi bi-trophy me-2\"></i> Competitions\n         </Link>\n \n-        <Link to=\"/workshops\" className=\"list-group-item list-group-item-action\">\n+        <Link to=\"/dashboard/publisher/workshops\" className=\"list-group-item list-group-item-action\">\n           <i className=\"bi bi-easel me-2\"></i> Workshops\n         </Link>\n       </ul>\n     </div>\n"
                },
                {
                    "date": 1766922041248,
                    "content": "Index: \n===================================================================\n--- \n+++ \n@@ -3,9 +3,9 @@\n export default function Sidebar() {\n   return (\n     <div className=\"sidebar bg-white shadow-sm\" style={{ width: \"250px\", minHeight: \"100vh\" }}>\n       <div className=\"p-3 border-bottom\">\n-        <h4 className=\"fw-bold\">Unlock</h4>\n+        <h4 className=\"fw-bold\">Unlock S</h4>\n       </div>\n \n       <ul className=\"list-group list-group-flush mt-3\">\n         <Link to=\"/dashboard/publisher\" className=\"list-group-item list-group-item-action\">\n"
                },
                {
                    "date": 1766922298391,
                    "content": "Index: \n===================================================================\n--- \n+++ \n@@ -1,41 +1,35 @@\n-import { Link } from \"react-router-dom\";\n+import { NavLink } from \"react-router-dom\";\n \n export default function Sidebar() {\n+  const menu = [\n+    { name: \"Dashboard\", icon: \"bi-speedometer2\", path: \"/dashboard/publisher\" },\n+    { name: \"Events\", icon: \"bi-calendar-event\", path: \"/dashboard/publisher/events\" },\n+    { name: \"Jobs\", icon: \"bi-briefcase\", path: \"/dashboard/publisher/jobs\" },\n+    { name: \"Startup Funding Calls\", icon: \"bi-cash-stack\", path: \"/dashboard/publisher/funding-calls\" },\n+    { name: \"Investor Programs\", icon: \"bi-graph-up-arrow\", path: \"/dashboard/publisher/investor-programs\" },\n+    { name: \"Competitions\", icon: \"bi-trophy\", path: \"/dashboard/publisher/competitions\" },\n+    { name: \"Workshops\", icon: \"bi-easel\", path: \"/dashboard/publisher/workshops\" }\n+  ];\n+\n   return (\n-    <div className=\"sidebar bg-white shadow-sm\" style={{ width: \"250px\", minHeight: \"100vh\" }}>\n-      <div className=\"p-3 border-bottom\">\n-        <h4 className=\"fw-bold\">Unlock S</h4>\n-      </div>\n+    <div className=\"sidebar-container\">\n+      <div className=\"sidebar-header\">Unlock</div>\n \n-      <ul className=\"list-group list-group-flush mt-3\">\n-        <Link to=\"/dashboard/publisher\" className=\"list-group-item list-group-item-action\">\n-          <i className=\"bi bi-speedometer2 me-2\"></i> Dashboard\n-        </Link>\n-\n-        <Link to=\"/dashboard/publisher/events\" className=\"list-group-item list-group-item-action\">\n-          <i className=\"bi bi-calendar-event me-2\"></i> Events\n-        </Link>\n-\n-        <Link to=\"/dashboard/publisher/jobs\" className=\"list-group-item list-group-item-action\">\n-          <i className=\"bi bi-briefcase me-2\"></i> Jobs\n-        </Link>\n-\n-        <Link to=\"/dashboard/publisher/funding-calls\" className=\"list-group-item list-group-item-action\">\n-          <i className=\"bi bi-cash-stack me-2\"></i> Startup Funding Calls\n-        </Link>\n-\n-        <Link to=\"/dashboard/publisher/investor-programs\" className=\"list-group-item list-group-item-action\">\n-          <i className=\"bi bi-graph-up-arrow me-2\"></i> Investor Programs\n-        </Link>\n-\n-        <Link to=\"/dashboard/publisher/competitions\" className=\"list-group-item list-group-item-action\">\n-          <i className=\"bi bi-trophy me-2\"></i> Competitions\n-        </Link>\n-\n-        <Link to=\"/dashboard/publisher/workshops\" className=\"list-group-item list-group-item-action\">\n-          <i className=\"bi bi-easel me-2\"></i> Workshops\n-        </Link>\n+      <ul className=\"sidebar-menu list-unstyled\">\n+        {menu.map((item) => (\n+          <li key={item.name}>\n+            <NavLink \n+              to={item.path} \n+              className={({ isActive }) =>\n+                \"sidebar-link \" + (isActive ? \"active\" : \"\")\n+              }\n+            >\n+              <i className={`bi ${item.icon} me-3`}></i>\n+              {item.name}\n+            </NavLink>\n+          </li>\n+        ))}\n       </ul>\n     </div>\n   );\n }\n"
                }
            ],
            "date": 1766862734823,
            "name": "Commit-0",
            "content": "import { Link } from \"react-router-dom\";\n\nexport default function Sidebar() {\n  return (\n    <div className=\"sidebar bg-white shadow-sm\" style={{ width: \"250px\", minHeight: \"100vh\" }}>\n      <div className=\"p-3 border-bottom\">\n        <h4 className=\"fw-bold\">Unlock</h4>\n      </div>\n\n      <ul className=\"list-group list-group-flush mt-3\">\n        <Link to=\"/dashboard\" className=\"list-group-item list-group-item-action\">\n          <i className=\"bi bi-speedometer2 me-2\"></i> Dashboard\n        </Link>\n\n        <Link to=\"/events\" className=\"list-group-item list-group-item-action\">\n          <i className=\"bi bi-calendar-event me-2\"></i> Events\n        </Link>\n\n        <Link to=\"/jobs\" className=\"list-group-item list-group-item-action\">\n          <i className=\"bi bi-briefcase me-2\"></i> Jobs\n        </Link>\n\n        <Link to=\"/funding-calls\" className=\"list-group-item list-group-item-action\">\n          <i className=\"bi bi-cash-stack me-2\"></i> Startup Funding Calls\n        </Link>\n\n        <Link to=\"/investor-programs\" className=\"list-group-item list-group-item-action\">\n          <i className=\"bi bi-graph-up-arrow me-2\"></i> Investor Programs\n        </Link>\n\n        <Link to=\"/competitions\" className=\"list-group-item list-group-item-action\">\n          <i className=\"bi bi-trophy me-2\"></i> Competitions\n        </Link>\n\n        <Link to=\"/workshops\" className=\"list-group-item list-group-item-action\">\n          <i className=\"bi bi-easel me-2\"></i> Workshops\n        </Link>\n      </ul>\n    </div>\n  );\n}\n"
        }
    ]
}